weighted_fair_allocation/__init__.py
weighted_fair_allocation/exceptions.py
weighted_fair_allocation/model.py
weighted_fair_allocation/utils.py
weighted_fair_allocation/algorithms/__init__.py
weighted_fair_allocation/algorithms/envy_cycle_elimination.py
weighted_fair_allocation/algorithms/nash_welfare.py
weighted_fair_allocation/algorithms/picking_sequences.py
weighted_fair_allocation/algorithms/weighted_adjusted_winner.py
weighted_fair_allocation/allocations/__init__.py
weighted_fair_allocation/allocations/envy_allocation.py
weighted_fair_allocation/allocations/nash_welfare_allocation.py
weighted_fair_allocation-1.0.0.dist-info/METADATA
weighted_fair_allocation-1.0.0.dist-info/WHEEL
weighted_fair_allocation-1.0.0.dist-info/licenses/LICENSE
weighted_fair_allocation-1.0.0.dist-info/RECORD
