Metadata-Version: 2.4
Name: weighted_fair_allocation
Version: 1.0.0
Summary: A realization of the weighted fair allocation problem, with implementations of common allocation algorithms. Created for experimentation purposes.
Author-email: Ties Tienhoven <ttienhoven+WFA@outlook.com>
License-Expression: MIT
License-File: LICENSE
Requires-Python: >=3.11
